data/Planets.csv
data/agn.csv
data/clcep.csv
data/cvnovag.csv
data/cvnovar.csv
data/dmcep.csv
data/dscut.csv
data/eb.csv
iar/BIARModel.py
iar/CIARModel.py
iar/IARModel.py
iar/__init__.py
iar/data_iar.py
iar/utils.py
iar-1.2.9.dist-info/METADATA
iar-1.2.9.dist-info/WHEEL
iar-1.2.9.dist-info/top_level.txt
iar-1.2.9.dist-info/RECORD
