Metadata-Version: 2.1
Name: iar
Version: 1.2.9
Summary: Irregularly Observed Autoregressive Models
Home-page: https://github.com/felipeelorrieta/iAR
Download-URL: https://github.com/felipeelorrieta/iAR/archive/refs/tags/v1.0.0.tar.gz
Author: Felipe Elorrieta
Author-email: felipe.elorrieta@usach.cl
License: MIT
Keywords: irregulary observed time series,autoregressive
Requires-Dist: numpy
Requires-Dist: pandas
Requires-Dist: scipy
Requires-Dist: matplotlib
Requires-Dist: scikit-learn
Requires-Dist: statsmodels
Requires-Dist: numba
